setup.py
webdry.py
test/test_flythrough.py
webdry.egg-info/PKG-INFO
webdry.egg-info/SOURCES.txt
webdry.egg-info/dependency_links.txt
webdry.egg-info/requires.txt
webdry.egg-info/top_level.txt