Metadata-Version: 1.0
Name: webdry
Version: 0.2
Summary: A set of functions for minimalistic interaction with Selenium WebDriver.
Home-page: https://bitbucket.org/niklasl/webdry
Author: Niklas Lindström
Author-email: lindstream@gmail.com
License: BSD
Keywords: web browser test tool
Platform: any
